audio_aligner-1.0.1.dist-info/DESCRIPTION.rst
audio_aligner-1.0.1.dist-info/METADATA
audio_aligner-1.0.1.dist-info/RECORD
audio_aligner-1.0.1.dist-info/WHEEL
audio_aligner-1.0.1.dist-info/metadata.json
audio_aligner-1.0.1.dist-info/top_level.txt
tf_audio_manager/__init__.py
