Metadata-Version: 2.0
Name: audio-aligner
Version: 1.0.1
Summary: UNKNOWN
Home-page: UNKNOWN
Author: longmao
Author-email: sharpcx@live.com
License: UNKNOWN
Platform: UNKNOWN
Classifier: Programming Language :: Python :: 3
Classifier: License :: OSI Approved :: MIT License
Classifier: Operating System :: OS Independent
Requires-Dist: requests
